{
  "id": "f9b7cc49-0cb5-4cfa-9200-a28982ad7a17",
  "prevId": "37219601-bbd3-4c8f-83db-d06f2db155a1",
  "version": "7",
  "dialect": "postgresql",
  "tables": {
    "public.projects": {
      "name": "projects",
      "schema": "",
      "columns": {
        "id": {
          "name": "id",
          "type": "text",
          "primaryKey": true,
          "notNull": true
        },
        "title": {
          "name": "title",
          "type": "text",
          "primaryKey": false,
          "notNull": true
        },
        "description": {
          "name": "description",
          "type": "text",
          "primaryKey": false,
          "notNull": false
        },
        "parent_id": {
          "name": "parent_id",
          "type": "text",
          "primaryKey": false,
          "notNull": false
        },
        "owner_id": {
          "name": "owner_id",
          "type": "text",
          "primaryKey": false,
          "notNull": false
        },
        "team_id": {
          "name": "team_id",
          "type": "text",
          "primaryKey": false,
          "notNull": false
        },
        "status": {
          "name": "status",
          "type": "text",
          "primaryKey": false,
          "notNull": true,
          "default": "'active'"
        },
        "start_date": {
          "name": "start_date",
          "type": "timestamp",
          "primaryKey": false,
          "notNull": false
        },
        "end_date": {
          "name": "end_date",
          "type": "timestamp",
          "primaryKey": false,
          "notNull": false
        },
        "color": {
          "name": "color",
          "type": "text",
          "primaryKey": false,
          "notNull": false,
          "default": "'#3B82F6'"
        },
        "icon": {
          "name": "icon",
          "type": "text",
          "primaryKey": false,
          "notNull": false
        },
        "settings": {
          "name": "settings",
          "type": "jsonb",
          "primaryKey": false,
          "notNull": false,
          "default": "'{}'::jsonb"
        },
        "template_id": {
          "name": "template_id",
          "type": "text",
          "primaryKey": false,
          "notNull": false
        },
        "custom_data": {
          "name": "custom_data",
          "type": "jsonb",
          "primaryKey": false,
          "notNull": false
        },
        "planner_slot": {
          "name": "planner_slot",
          "type": "jsonb",
          "primaryKey": false,
          "notNull": false
        },
        "created_at": {
          "name": "created_at",
          "type": "timestamp",
          "primaryKey": false,
          "notNull": true,
          "default": "now()"
        },
        "updated_at": {
          "name": "updated_at",
          "type": "timestamp",
          "primaryKey": false,
          "notNull": false,
          "default": "now()"
        },
        "deleted_at": {
          "name": "deleted_at",
          "type": "timestamp",
          "primaryKey": false,
          "notNull": false
        }
      },
      "indexes": {},
      "foreignKeys": {
        "projects_owner_id_users_id_fk": {
          "name": "projects_owner_id_users_id_fk",
          "tableFrom": "projects",
          "tableTo": "users",
          "columnsFrom": [
            "owner_id"
          ],
          "columnsTo": [
            "id"
          ],
          "onDelete": "no action",
          "onUpdate": "no action"
        },
        "projects_team_id_teams_id_fk": {
          "name": "projects_team_id_teams_id_fk",
          "tableFrom": "projects",
          "tableTo": "teams",
          "columnsFrom": [
            "team_id"
          ],
          "columnsTo": [
            "id"
          ],
          "onDelete": "no action",
          "onUpdate": "no action"
        },
        "projects_template_id_templates_id_fk": {
          "name": "projects_template_id_templates_id_fk",
          "tableFrom": "projects",
          "tableTo": "templates",
          "columnsFrom": [
            "template_id"
          ],
          "columnsTo": [
            "id"
          ],
          "onDelete": "no action",
          "onUpdate": "no action"
        }
      },
      "compositePrimaryKeys": {},
      "uniqueConstraints": {}
    },
    "public.subtasks": {
      "name": "subtasks",
      "schema": "",
      "columns": {
        "id": {
          "name": "id",
          "type": "text",
          "primaryKey": true,
          "notNull": true
        },
        "name": {
          "name": "name",
          "type": "text",
          "primaryKey": false,
          "notNull": true
        },
        "task_id": {
          "name": "task_id",
          "type": "text",
          "primaryKey": false,
          "notNull": true
        },
        "status": {
          "name": "status",
          "type": "text",
          "primaryKey": false,
          "notNull": false,
          "default": "'pendente'"
        },
        "is_done": {
          "name": "is_done",
          "type": "boolean",
          "primaryKey": false,
          "notNull": false,
          "default": false
        },
        "created_at": {
          "name": "created_at",
          "type": "timestamp",
          "primaryKey": false,
          "notNull": false,
          "default": "now()"
        },
        "updated_at": {
          "name": "updated_at",
          "type": "timestamp",
          "primaryKey": false,
          "notNull": false,
          "default": "now()"
        }
      },
      "indexes": {},
      "foreignKeys": {
        "subtasks_task_id_tasks_id_fk": {
          "name": "subtasks_task_id_tasks_id_fk",
          "tableFrom": "subtasks",
          "tableTo": "tasks",
          "columnsFrom": [
            "task_id"
          ],
          "columnsTo": [
            "id"
          ],
          "onDelete": "cascade",
          "onUpdate": "no action"
        }
      },
      "compositePrimaryKeys": {},
      "uniqueConstraints": {}
    },
    "public.tags": {
      "name": "tags",
      "schema": "",
      "columns": {
        "id": {
          "name": "id",
          "type": "text",
          "primaryKey": true,
          "notNull": true
        },
        "name": {
          "name": "name",
          "type": "text",
          "primaryKey": false,
          "notNull": true
        },
        "color": {
          "name": "color",
          "type": "text",
          "primaryKey": false,
          "notNull": false,
          "default": "'#94a3b8'"
        },
        "icon": {
          "name": "icon",
          "type": "text",
          "primaryKey": false,
          "notNull": false
        },
        "usage_count": {
          "name": "usage_count",
          "type": "integer",
          "primaryKey": false,
          "notNull": false,
          "default": 0
        },
        "created_at": {
          "name": "created_at",
          "type": "timestamp",
          "primaryKey": false,
          "notNull": false,
          "default": "now()"
        }
      },
      "indexes": {},
      "foreignKeys": {},
      "compositePrimaryKeys": {},
      "uniqueConstraints": {
        "tags_name_unique": {
          "name": "tags_name_unique",
          "nullsNotDistinct": false,
          "columns": [
            "name"
          ]
        }
      }
    },
    "public.task_dependencies": {
      "name": "task_dependencies",
      "schema": "",
      "columns": {
        "id": {
          "name": "id",
          "type": "text",
          "primaryKey": true,
          "notNull": true
        },
        "source_task_id": {
          "name": "source_task_id",
          "type": "text",
          "primaryKey": false,
          "notNull": true
        },
        "target_task_id": {
          "name": "target_task_id",
          "type": "text",
          "primaryKey": false,
          "notNull": true
        },
        "type": {
          "name": "type",
          "type": "text",
          "primaryKey": false,
          "notNull": false,
          "default": "'dependency'"
        },
        "created_at": {
          "name": "created_at",
          "type": "timestamp",
          "primaryKey": false,
          "notNull": false,
          "default": "now()"
        }
      },
      "indexes": {},
      "foreignKeys": {
        "task_dependencies_source_task_id_tasks_id_fk": {
          "name": "task_dependencies_source_task_id_tasks_id_fk",
          "tableFrom": "task_dependencies",
          "tableTo": "tasks",
          "columnsFrom": [
            "source_task_id"
          ],
          "columnsTo": [
            "id"
          ],
          "onDelete": "cascade",
          "onUpdate": "no action"
        },
        "task_dependencies_target_task_id_tasks_id_fk": {
          "name": "task_dependencies_target_task_id_tasks_id_fk",
          "tableFrom": "task_dependencies",
          "tableTo": "tasks",
          "columnsFrom": [
            "target_task_id"
          ],
          "columnsTo": [
            "id"
          ],
          "onDelete": "cascade",
          "onUpdate": "no action"
        }
      },
      "compositePrimaryKeys": {},
      "uniqueConstraints": {}
    },
    "public.task_tags": {
      "name": "task_tags",
      "schema": "",
      "columns": {
        "task_id": {
          "name": "task_id",
          "type": "text",
          "primaryKey": false,
          "notNull": true
        },
        "tag_id": {
          "name": "tag_id",
          "type": "text",
          "primaryKey": false,
          "notNull": true
        }
      },
      "indexes": {},
      "foreignKeys": {
        "task_tags_task_id_tasks_id_fk": {
          "name": "task_tags_task_id_tasks_id_fk",
          "tableFrom": "task_tags",
          "tableTo": "tasks",
          "columnsFrom": [
            "task_id"
          ],
          "columnsTo": [
            "id"
          ],
          "onDelete": "cascade",
          "onUpdate": "no action"
        },
        "task_tags_tag_id_tags_id_fk": {
          "name": "task_tags_tag_id_tags_id_fk",
          "tableFrom": "task_tags",
          "tableTo": "tags",
          "columnsFrom": [
            "tag_id"
          ],
          "columnsTo": [
            "id"
          ],
          "onDelete": "cascade",
          "onUpdate": "no action"
        }
      },
      "compositePrimaryKeys": {
        "task_tags_task_id_tag_id_pk": {
          "name": "task_tags_task_id_tag_id_pk",
          "columns": [
            "task_id",
            "tag_id"
          ]
        }
      },
      "uniqueConstraints": {}
    },
    "public.tasks": {
      "name": "tasks",
      "schema": "",
      "columns": {
        "id": {
          "name": "id",
          "type": "text",
          "primaryKey": true,
          "notNull": true
        },
        "title": {
          "name": "title",
          "type": "text",
          "primaryKey": false,
          "notNull": true
        },
        "description": {
          "name": "description",
          "type": "text",
          "primaryKey": false,
          "notNull": false
        },
        "project_id": {
          "name": "project_id",
          "type": "text",
          "primaryKey": false,
          "notNull": false
        },
        "parent_id": {
          "name": "parent_id",
          "type": "text",
          "primaryKey": false,
          "notNull": false
        },
        "owner_id": {
          "name": "owner_id",
          "type": "text",
          "primaryKey": false,
          "notNull": false
        },
        "team_id": {
          "name": "team_id",
          "type": "text",
          "primaryKey": false,
          "notNull": false
        },
        "status": {
          "name": "status",
          "type": "text",
          "primaryKey": false,
          "notNull": true,
          "default": "'todo'"
        },
        "priority": {
          "name": "priority",
          "type": "text",
          "primaryKey": false,
          "notNull": false,
          "default": "'medium'"
        },
        "order": {
          "name": "order",
          "type": "integer",
          "primaryKey": false,
          "notNull": false,
          "default": 0
        },
        "due_date": {
          "name": "due_date",
          "type": "timestamp",
          "primaryKey": false,
          "notNull": false
        },
        "estimated_hours": {
          "name": "estimated_hours",
          "type": "integer",
          "primaryKey": false,
          "notNull": false
        },
        "is_done": {
          "name": "is_done",
          "type": "boolean",
          "primaryKey": false,
          "notNull": false,
          "default": false
        },
        "checklist": {
          "name": "checklist",
          "type": "jsonb",
          "primaryKey": false,
          "notNull": false
        },
        "tags_preview": {
          "name": "tags_preview",
          "type": "jsonb",
          "primaryKey": false,
          "notNull": false
        },
        "energy_tags": {
          "name": "energy_tags",
          "type": "jsonb",
          "primaryKey": false,
          "notNull": false
        },
        "energy_impact": {
          "name": "energy_impact",
          "type": "text",
          "primaryKey": false,
          "notNull": false,
          "default": "'neutro'"
        },
        "recurrence": {
          "name": "recurrence",
          "type": "jsonb",
          "primaryKey": false,
          "notNull": false
        },
        "chain_connections": {
          "name": "chain_connections",
          "type": "jsonb",
          "primaryKey": false,
          "notNull": false
        },
        "template_id": {
          "name": "template_id",
          "type": "text",
          "primaryKey": false,
          "notNull": false
        },
        "custom_data": {
          "name": "custom_data",
          "type": "jsonb",
          "primaryKey": false,
          "notNull": false
        },
        "planner_slot": {
          "name": "planner_slot",
          "type": "jsonb",
          "primaryKey": false,
          "notNull": false
        },
        "related_files_count": {
          "name": "related_files_count",
          "type": "integer",
          "primaryKey": false,
          "notNull": false,
          "default": 0
        },
        "created_at": {
          "name": "created_at",
          "type": "timestamp",
          "primaryKey": false,
          "notNull": true,
          "default": "now()"
        },
        "updated_at": {
          "name": "updated_at",
          "type": "timestamp",
          "primaryKey": false,
          "notNull": false,
          "default": "now()"
        },
        "deleted_at": {
          "name": "deleted_at",
          "type": "timestamp",
          "primaryKey": false,
          "notNull": false
        }
      },
      "indexes": {},
      "foreignKeys": {
        "tasks_project_id_projects_id_fk": {
          "name": "tasks_project_id_projects_id_fk",
          "tableFrom": "tasks",
          "tableTo": "projects",
          "columnsFrom": [
            "project_id"
          ],
          "columnsTo": [
            "id"
          ],
          "onDelete": "cascade",
          "onUpdate": "no action"
        },
        "tasks_owner_id_users_id_fk": {
          "name": "tasks_owner_id_users_id_fk",
          "tableFrom": "tasks",
          "tableTo": "users",
          "columnsFrom": [
            "owner_id"
          ],
          "columnsTo": [
            "id"
          ],
          "onDelete": "no action",
          "onUpdate": "no action"
        },
        "tasks_team_id_teams_id_fk": {
          "name": "tasks_team_id_teams_id_fk",
          "tableFrom": "tasks",
          "tableTo": "teams",
          "columnsFrom": [
            "team_id"
          ],
          "columnsTo": [
            "id"
          ],
          "onDelete": "no action",
          "onUpdate": "no action"
        },
        "tasks_template_id_templates_id_fk": {
          "name": "tasks_template_id_templates_id_fk",
          "tableFrom": "tasks",
          "tableTo": "templates",
          "columnsFrom": [
            "template_id"
          ],
          "columnsTo": [
            "id"
          ],
          "onDelete": "no action",
          "onUpdate": "no action"
        }
      },
      "compositePrimaryKeys": {},
      "uniqueConstraints": {}
    },
    "public.team_invites": {
      "name": "team_invites",
      "schema": "",
      "columns": {
        "id": {
          "name": "id",
          "type": "text",
          "primaryKey": true,
          "notNull": true
        },
        "team_id": {
          "name": "team_id",
          "type": "text",
          "primaryKey": false,
          "notNull": true
        },
        "email": {
          "name": "email",
          "type": "text",
          "primaryKey": false,
          "notNull": true
        },
        "role": {
          "name": "role",
          "type": "text",
          "primaryKey": false,
          "notNull": false,
          "default": "'editor'"
        },
        "status": {
          "name": "status",
          "type": "text",
          "primaryKey": false,
          "notNull": false,
          "default": "'pending'"
        },
        "created_at": {
          "name": "created_at",
          "type": "timestamp",
          "primaryKey": false,
          "notNull": false,
          "default": "now()"
        }
      },
      "indexes": {},
      "foreignKeys": {
        "team_invites_team_id_teams_id_fk": {
          "name": "team_invites_team_id_teams_id_fk",
          "tableFrom": "team_invites",
          "tableTo": "teams",
          "columnsFrom": [
            "team_id"
          ],
          "columnsTo": [
            "id"
          ],
          "onDelete": "no action",
          "onUpdate": "no action"
        }
      },
      "compositePrimaryKeys": {},
      "uniqueConstraints": {}
    },
    "public.team_members": {
      "name": "team_members",
      "schema": "",
      "columns": {
        "id": {
          "name": "id",
          "type": "text",
          "primaryKey": true,
          "notNull": true
        },
        "team_id": {
          "name": "team_id",
          "type": "text",
          "primaryKey": false,
          "notNull": true
        },
        "user_id": {
          "name": "user_id",
          "type": "text",
          "primaryKey": false,
          "notNull": true
        },
        "role": {
          "name": "role",
          "type": "text",
          "primaryKey": false,
          "notNull": false,
          "default": "'editor'"
        },
        "energy_status": {
          "name": "energy_status",
          "type": "integer",
          "primaryKey": false,
          "notNull": false,
          "default": 100
        },
        "work_load": {
          "name": "work_load",
          "type": "integer",
          "primaryKey": false,
          "notNull": false,
          "default": 0
        },
        "status": {
          "name": "status",
          "type": "text",
          "primaryKey": false,
          "notNull": false,
          "default": "'offline'"
        },
        "joined_at": {
          "name": "joined_at",
          "type": "timestamp",
          "primaryKey": false,
          "notNull": false,
          "default": "now()"
        }
      },
      "indexes": {},
      "foreignKeys": {
        "team_members_team_id_teams_id_fk": {
          "name": "team_members_team_id_teams_id_fk",
          "tableFrom": "team_members",
          "tableTo": "teams",
          "columnsFrom": [
            "team_id"
          ],
          "columnsTo": [
            "id"
          ],
          "onDelete": "cascade",
          "onUpdate": "no action"
        },
        "team_members_user_id_users_id_fk": {
          "name": "team_members_user_id_users_id_fk",
          "tableFrom": "team_members",
          "tableTo": "users",
          "columnsFrom": [
            "user_id"
          ],
          "columnsTo": [
            "id"
          ],
          "onDelete": "cascade",
          "onUpdate": "no action"
        }
      },
      "compositePrimaryKeys": {},
      "uniqueConstraints": {}
    },
    "public.teams": {
      "name": "teams",
      "schema": "",
      "columns": {
        "id": {
          "name": "id",
          "type": "text",
          "primaryKey": true,
          "notNull": true
        },
        "name": {
          "name": "name",
          "type": "text",
          "primaryKey": false,
          "notNull": true
        },
        "description": {
          "name": "description",
          "type": "text",
          "primaryKey": false,
          "notNull": false
        },
        "color": {
          "name": "color",
          "type": "text",
          "primaryKey": false,
          "notNull": false
        },
        "owner_id": {
          "name": "owner_id",
          "type": "text",
          "primaryKey": false,
          "notNull": false
        },
        "created_at": {
          "name": "created_at",
          "type": "timestamp",
          "primaryKey": false,
          "notNull": true,
          "default": "now()"
        },
        "updated_at": {
          "name": "updated_at",
          "type": "timestamp",
          "primaryKey": false,
          "notNull": false,
          "default": "now()"
        }
      },
      "indexes": {},
      "foreignKeys": {
        "teams_owner_id_users_id_fk": {
          "name": "teams_owner_id_users_id_fk",
          "tableFrom": "teams",
          "tableTo": "users",
          "columnsFrom": [
            "owner_id"
          ],
          "columnsTo": [
            "id"
          ],
          "onDelete": "no action",
          "onUpdate": "no action"
        }
      },
      "compositePrimaryKeys": {},
      "uniqueConstraints": {}
    },
    "public.templates": {
      "name": "templates",
      "schema": "",
      "columns": {
        "id": {
          "name": "id",
          "type": "text",
          "primaryKey": true,
          "notNull": true
        },
        "name": {
          "name": "name",
          "type": "text",
          "primaryKey": false,
          "notNull": true
        },
        "description": {
          "name": "description",
          "type": "text",
          "primaryKey": false,
          "notNull": false
        },
        "type": {
          "name": "type",
          "type": "text",
          "primaryKey": false,
          "notNull": true
        },
        "structure": {
          "name": "structure",
          "type": "jsonb",
          "primaryKey": false,
          "notNull": true
        },
        "created_by": {
          "name": "created_by",
          "type": "text",
          "primaryKey": false,
          "notNull": true
        },
        "created_at": {
          "name": "created_at",
          "type": "timestamp",
          "primaryKey": false,
          "notNull": true,
          "default": "now()"
        }
      },
      "indexes": {},
      "foreignKeys": {},
      "compositePrimaryKeys": {},
      "uniqueConstraints": {}
    },
    "public.users": {
      "name": "users",
      "schema": "",
      "columns": {
        "id": {
          "name": "id",
          "type": "text",
          "primaryKey": true,
          "notNull": true
        },
        "name": {
          "name": "name",
          "type": "text",
          "primaryKey": false,
          "notNull": true
        },
        "email": {
          "name": "email",
          "type": "text",
          "primaryKey": false,
          "notNull": true
        },
        "password_hash": {
          "name": "password_hash",
          "type": "text",
          "primaryKey": false,
          "notNull": false
        },
        "avatar_url": {
          "name": "avatar_url",
          "type": "text",
          "primaryKey": false,
          "notNull": false
        },
        "credits": {
          "name": "credits",
          "type": "integer",
          "primaryKey": false,
          "notNull": false,
          "default": 100
        },
        "role": {
          "name": "role",
          "type": "text",
          "primaryKey": false,
          "notNull": true,
          "default": "'user'"
        },
        "ai_settings": {
          "name": "ai_settings",
          "type": "jsonb",
          "primaryKey": false,
          "notNull": false,
          "default": "'{}'::jsonb"
        },
        "dashboard_preferences": {
          "name": "dashboard_preferences",
          "type": "jsonb",
          "primaryKey": false,
          "notNull": false,
          "default": "'{\"sankalpa\":true,\"projects\":true,\"tasks\":true,\"velocity\":true,\"astral\":true,\"rituals\":true,\"energy\":true,\"mood\":true,\"tags\":true,\"ash\":true,\"menstrualCycle\":true}'::jsonb"
        },
        "created_at": {
          "name": "created_at",
          "type": "timestamp",
          "primaryKey": false,
          "notNull": true,
          "default": "now()"
        },
        "updated_at": {
          "name": "updated_at",
          "type": "timestamp",
          "primaryKey": false,
          "notNull": false,
          "default": "now()"
        }
      },
      "indexes": {},
      "foreignKeys": {},
      "compositePrimaryKeys": {},
      "uniqueConstraints": {
        "users_email_unique": {
          "name": "users_email_unique",
          "nullsNotDistinct": false,
          "columns": [
            "email"
          ]
        }
      }
    },
    "public.goals": {
      "name": "goals",
      "schema": "",
      "columns": {
        "id": {
          "name": "id",
          "type": "text",
          "primaryKey": true,
          "notNull": true
        },
        "sankalpa_id": {
          "name": "sankalpa_id",
          "type": "text",
          "primaryKey": false,
          "notNull": false
        },
        "title": {
          "name": "title",
          "type": "text",
          "primaryKey": false,
          "notNull": true
        },
        "metric": {
          "name": "metric",
          "type": "text",
          "primaryKey": false,
          "notNull": false
        },
        "target_value": {
          "name": "target_value",
          "type": "text",
          "primaryKey": false,
          "notNull": false
        },
        "current_value": {
          "name": "current_value",
          "type": "text",
          "primaryKey": false,
          "notNull": false
        },
        "deadline": {
          "name": "deadline",
          "type": "timestamp",
          "primaryKey": false,
          "notNull": false
        },
        "is_completed": {
          "name": "is_completed",
          "type": "boolean",
          "primaryKey": false,
          "notNull": false,
          "default": false
        },
        "created_at": {
          "name": "created_at",
          "type": "timestamp",
          "primaryKey": false,
          "notNull": false,
          "default": "now()"
        },
        "updated_at": {
          "name": "updated_at",
          "type": "timestamp",
          "primaryKey": false,
          "notNull": false,
          "default": "now()"
        }
      },
      "indexes": {},
      "foreignKeys": {
        "goals_sankalpa_id_sankalpas_id_fk": {
          "name": "goals_sankalpa_id_sankalpas_id_fk",
          "tableFrom": "goals",
          "tableTo": "sankalpas",
          "columnsFrom": [
            "sankalpa_id"
          ],
          "columnsTo": [
            "id"
          ],
          "onDelete": "cascade",
          "onUpdate": "no action"
        }
      },
      "compositePrimaryKeys": {},
      "uniqueConstraints": {}
    },
    "public.routines": {
      "name": "routines",
      "schema": "",
      "columns": {
        "id": {
          "name": "id",
          "type": "text",
          "primaryKey": true,
          "notNull": true
        },
        "user_id": {
          "name": "user_id",
          "type": "text",
          "primaryKey": false,
          "notNull": false
        },
        "title": {
          "name": "title",
          "type": "text",
          "primaryKey": false,
          "notNull": true
        },
        "type": {
          "name": "type",
          "type": "text",
          "primaryKey": false,
          "notNull": true
        },
        "start_hour": {
          "name": "start_hour",
          "type": "integer",
          "primaryKey": false,
          "notNull": true
        },
        "end_hour": {
          "name": "end_hour",
          "type": "integer",
          "primaryKey": false,
          "notNull": true
        },
        "days": {
          "name": "days",
          "type": "jsonb",
          "primaryKey": false,
          "notNull": false
        },
        "icon": {
          "name": "icon",
          "type": "text",
          "primaryKey": false,
          "notNull": false
        },
        "created_at": {
          "name": "created_at",
          "type": "timestamp",
          "primaryKey": false,
          "notNull": false,
          "default": "now()"
        }
      },
      "indexes": {},
      "foreignKeys": {
        "routines_user_id_users_id_fk": {
          "name": "routines_user_id_users_id_fk",
          "tableFrom": "routines",
          "tableTo": "users",
          "columnsFrom": [
            "user_id"
          ],
          "columnsTo": [
            "id"
          ],
          "onDelete": "cascade",
          "onUpdate": "no action"
        }
      },
      "compositePrimaryKeys": {},
      "uniqueConstraints": {}
    },
    "public.sankalpas": {
      "name": "sankalpas",
      "schema": "",
      "columns": {
        "id": {
          "name": "id",
          "type": "text",
          "primaryKey": true,
          "notNull": true
        },
        "title": {
          "name": "title",
          "type": "text",
          "primaryKey": false,
          "notNull": true
        },
        "description": {
          "name": "description",
          "type": "text",
          "primaryKey": false,
          "notNull": false
        },
        "user_id": {
          "name": "user_id",
          "type": "text",
          "primaryKey": false,
          "notNull": false
        },
        "team_id": {
          "name": "team_id",
          "type": "text",
          "primaryKey": false,
          "notNull": false
        },
        "status": {
          "name": "status",
          "type": "text",
          "primaryKey": false,
          "notNull": false,
          "default": "'ativo'"
        },
        "year": {
          "name": "year",
          "type": "text",
          "primaryKey": false,
          "notNull": false
        },
        "quarter": {
          "name": "quarter",
          "type": "text",
          "primaryKey": false,
          "notNull": false
        },
        "pillars": {
          "name": "pillars",
          "type": "jsonb",
          "primaryKey": false,
          "notNull": false
        },
        "created_at": {
          "name": "created_at",
          "type": "timestamp",
          "primaryKey": false,
          "notNull": false,
          "default": "now()"
        },
        "updated_at": {
          "name": "updated_at",
          "type": "timestamp",
          "primaryKey": false,
          "notNull": false,
          "default": "now()"
        }
      },
      "indexes": {},
      "foreignKeys": {
        "sankalpas_user_id_users_id_fk": {
          "name": "sankalpas_user_id_users_id_fk",
          "tableFrom": "sankalpas",
          "tableTo": "users",
          "columnsFrom": [
            "user_id"
          ],
          "columnsTo": [
            "id"
          ],
          "onDelete": "cascade",
          "onUpdate": "no action"
        },
        "sankalpas_team_id_teams_id_fk": {
          "name": "sankalpas_team_id_teams_id_fk",
          "tableFrom": "sankalpas",
          "tableTo": "teams",
          "columnsFrom": [
            "team_id"
          ],
          "columnsTo": [
            "id"
          ],
          "onDelete": "cascade",
          "onUpdate": "no action"
        }
      },
      "compositePrimaryKeys": {},
      "uniqueConstraints": {}
    },
    "public.time_sessions": {
      "name": "time_sessions",
      "schema": "",
      "columns": {
        "id": {
          "name": "id",
          "type": "text",
          "primaryKey": true,
          "notNull": true
        },
        "user_id": {
          "name": "user_id",
          "type": "text",
          "primaryKey": false,
          "notNull": true
        },
        "task_id": {
          "name": "task_id",
          "type": "text",
          "primaryKey": false,
          "notNull": false
        },
        "project_id": {
          "name": "project_id",
          "type": "text",
          "primaryKey": false,
          "notNull": false
        },
        "duration_seconds": {
          "name": "duration_seconds",
          "type": "integer",
          "primaryKey": false,
          "notNull": true
        },
        "start_time": {
          "name": "start_time",
          "type": "timestamp with time zone",
          "primaryKey": false,
          "notNull": true
        },
        "end_time": {
          "name": "end_time",
          "type": "timestamp with time zone",
          "primaryKey": false,
          "notNull": false
        },
        "focus_rating": {
          "name": "focus_rating",
          "type": "integer",
          "primaryKey": false,
          "notNull": false
        },
        "notes": {
          "name": "notes",
          "type": "text",
          "primaryKey": false,
          "notNull": false
        },
        "created_at": {
          "name": "created_at",
          "type": "timestamp with time zone",
          "primaryKey": false,
          "notNull": false,
          "default": "now()"
        }
      },
      "indexes": {},
      "foreignKeys": {
        "time_sessions_user_id_users_id_fk": {
          "name": "time_sessions_user_id_users_id_fk",
          "tableFrom": "time_sessions",
          "tableTo": "users",
          "columnsFrom": [
            "user_id"
          ],
          "columnsTo": [
            "id"
          ],
          "onDelete": "cascade",
          "onUpdate": "no action"
        },
        "time_sessions_task_id_tasks_id_fk": {
          "name": "time_sessions_task_id_tasks_id_fk",
          "tableFrom": "time_sessions",
          "tableTo": "tasks",
          "columnsFrom": [
            "task_id"
          ],
          "columnsTo": [
            "id"
          ],
          "onDelete": "no action",
          "onUpdate": "no action"
        },
        "time_sessions_project_id_projects_id_fk": {
          "name": "time_sessions_project_id_projects_id_fk",
          "tableFrom": "time_sessions",
          "tableTo": "projects",
          "columnsFrom": [
            "project_id"
          ],
          "columnsTo": [
            "id"
          ],
          "onDelete": "no action",
          "onUpdate": "no action"
        }
      },
      "compositePrimaryKeys": {},
      "uniqueConstraints": {}
    },
    "public.weekly_tasks": {
      "name": "weekly_tasks",
      "schema": "",
      "columns": {
        "id": {
          "name": "id",
          "type": "text",
          "primaryKey": true,
          "notNull": true
        },
        "user_id": {
          "name": "user_id",
          "type": "text",
          "primaryKey": false,
          "notNull": false
        },
        "task_id": {
          "name": "task_id",
          "type": "text",
          "primaryKey": false,
          "notNull": false
        },
        "content": {
          "name": "content",
          "type": "text",
          "primaryKey": false,
          "notNull": true
        },
        "week_start_date": {
          "name": "week_start_date",
          "type": "date",
          "primaryKey": false,
          "notNull": true
        },
        "day_of_week": {
          "name": "day_of_week",
          "type": "text",
          "primaryKey": false,
          "notNull": true
        },
        "status": {
          "name": "status",
          "type": "text",
          "primaryKey": false,
          "notNull": false,
          "default": "'todo'"
        },
        "type": {
          "name": "type",
          "type": "text",
          "primaryKey": false,
          "notNull": false,
          "default": "'task'"
        },
        "time_block": {
          "name": "time_block",
          "type": "text",
          "primaryKey": false,
          "notNull": false
        },
        "created_at": {
          "name": "created_at",
          "type": "timestamp",
          "primaryKey": false,
          "notNull": false,
          "default": "now()"
        }
      },
      "indexes": {},
      "foreignKeys": {
        "weekly_tasks_user_id_users_id_fk": {
          "name": "weekly_tasks_user_id_users_id_fk",
          "tableFrom": "weekly_tasks",
          "tableTo": "users",
          "columnsFrom": [
            "user_id"
          ],
          "columnsTo": [
            "id"
          ],
          "onDelete": "cascade",
          "onUpdate": "no action"
        },
        "weekly_tasks_task_id_tasks_id_fk": {
          "name": "weekly_tasks_task_id_tasks_id_fk",
          "tableFrom": "weekly_tasks",
          "tableTo": "tasks",
          "columnsFrom": [
            "task_id"
          ],
          "columnsTo": [
            "id"
          ],
          "onDelete": "cascade",
          "onUpdate": "no action"
        }
      },
      "compositePrimaryKeys": {},
      "uniqueConstraints": {}
    },
    "public.file_task_associations": {
      "name": "file_task_associations",
      "schema": "",
      "columns": {
        "id": {
          "name": "id",
          "type": "text",
          "primaryKey": true,
          "notNull": true
        },
        "file_id": {
          "name": "file_id",
          "type": "text",
          "primaryKey": false,
          "notNull": true
        },
        "task_id": {
          "name": "task_id",
          "type": "text",
          "primaryKey": false,
          "notNull": true
        },
        "document_type": {
          "name": "document_type",
          "type": "text",
          "primaryKey": false,
          "notNull": false,
          "default": "'note'"
        },
        "relationship": {
          "name": "relationship",
          "type": "text",
          "primaryKey": false,
          "notNull": false,
          "default": "'modify'"
        },
        "created_at": {
          "name": "created_at",
          "type": "timestamp",
          "primaryKey": false,
          "notNull": false,
          "default": "now()"
        },
        "created_by": {
          "name": "created_by",
          "type": "text",
          "primaryKey": false,
          "notNull": false
        },
        "is_active": {
          "name": "is_active",
          "type": "boolean",
          "primaryKey": false,
          "notNull": false,
          "default": true
        }
      },
      "indexes": {
        "file_task_associations_file_id_index": {
          "name": "file_task_associations_file_id_index",
          "columns": [
            {
              "expression": "file_id",
              "isExpression": false,
              "asc": true,
              "nulls": "last"
            }
          ],
          "isUnique": false,
          "concurrently": false,
          "method": "btree",
          "with": {}
        },
        "file_task_associations_task_id_index": {
          "name": "file_task_associations_task_id_index",
          "columns": [
            {
              "expression": "task_id",
              "isExpression": false,
              "asc": true,
              "nulls": "last"
            }
          ],
          "isUnique": false,
          "concurrently": false,
          "method": "btree",
          "with": {}
        }
      },
      "foreignKeys": {
        "file_task_associations_file_id_papyrus_documents_id_fk": {
          "name": "file_task_associations_file_id_papyrus_documents_id_fk",
          "tableFrom": "file_task_associations",
          "tableTo": "papyrus_documents",
          "columnsFrom": [
            "file_id"
          ],
          "columnsTo": [
            "id"
          ],
          "onDelete": "cascade",
          "onUpdate": "no action"
        },
        "file_task_associations_task_id_tasks_id_fk": {
          "name": "file_task_associations_task_id_tasks_id_fk",
          "tableFrom": "file_task_associations",
          "tableTo": "tasks",
          "columnsFrom": [
            "task_id"
          ],
          "columnsTo": [
            "id"
          ],
          "onDelete": "cascade",
          "onUpdate": "no action"
        },
        "file_task_associations_created_by_users_id_fk": {
          "name": "file_task_associations_created_by_users_id_fk",
          "tableFrom": "file_task_associations",
          "tableTo": "users",
          "columnsFrom": [
            "created_by"
          ],
          "columnsTo": [
            "id"
          ],
          "onDelete": "set null",
          "onUpdate": "no action"
        }
      },
      "compositePrimaryKeys": {
        "file_task_associations_file_id_task_id_pk": {
          "name": "file_task_associations_file_id_task_id_pk",
          "columns": [
            "file_id",
            "task_id"
          ]
        }
      },
      "uniqueConstraints": {}
    },
    "public.mind_map_edges": {
      "name": "mind_map_edges",
      "schema": "",
      "columns": {
        "id": {
          "name": "id",
          "type": "text",
          "primaryKey": true,
          "notNull": true
        },
        "map_id": {
          "name": "map_id",
          "type": "text",
          "primaryKey": false,
          "notNull": true
        },
        "source_id": {
          "name": "source_id",
          "type": "text",
          "primaryKey": false,
          "notNull": true
        },
        "target_id": {
          "name": "target_id",
          "type": "text",
          "primaryKey": false,
          "notNull": true
        },
        "type": {
          "name": "type",
          "type": "text",
          "primaryKey": false,
          "notNull": false,
          "default": "'smoothstep'"
        },
        "animated": {
          "name": "animated",
          "type": "boolean",
          "primaryKey": false,
          "notNull": false,
          "default": true
        },
        "label": {
          "name": "label",
          "type": "text",
          "primaryKey": false,
          "notNull": false
        },
        "created_at": {
          "name": "created_at",
          "type": "timestamp",
          "primaryKey": false,
          "notNull": false,
          "default": "now()"
        }
      },
      "indexes": {},
      "foreignKeys": {
        "mind_map_edges_map_id_mind_maps_id_fk": {
          "name": "mind_map_edges_map_id_mind_maps_id_fk",
          "tableFrom": "mind_map_edges",
          "tableTo": "mind_maps",
          "columnsFrom": [
            "map_id"
          ],
          "columnsTo": [
            "id"
          ],
          "onDelete": "cascade",
          "onUpdate": "no action"
        },
        "mind_map_edges_source_id_mind_map_nodes_id_fk": {
          "name": "mind_map_edges_source_id_mind_map_nodes_id_fk",
          "tableFrom": "mind_map_edges",
          "tableTo": "mind_map_nodes",
          "columnsFrom": [
            "source_id"
          ],
          "columnsTo": [
            "id"
          ],
          "onDelete": "cascade",
          "onUpdate": "no action"
        },
        "mind_map_edges_target_id_mind_map_nodes_id_fk": {
          "name": "mind_map_edges_target_id_mind_map_nodes_id_fk",
          "tableFrom": "mind_map_edges",
          "tableTo": "mind_map_nodes",
          "columnsFrom": [
            "target_id"
          ],
          "columnsTo": [
            "id"
          ],
          "onDelete": "cascade",
          "onUpdate": "no action"
        }
      },
      "compositePrimaryKeys": {},
      "uniqueConstraints": {}
    },
    "public.mind_map_nodes": {
      "name": "mind_map_nodes",
      "schema": "",
      "columns": {
        "id": {
          "name": "id",
          "type": "text",
          "primaryKey": true,
          "notNull": true
        },
        "map_id": {
          "name": "map_id",
          "type": "text",
          "primaryKey": false,
          "notNull": true
        },
        "label": {
          "name": "label",
          "type": "text",
          "primaryKey": false,
          "notNull": true
        },
        "type": {
          "name": "type",
          "type": "text",
          "primaryKey": false,
          "notNull": false,
          "default": "'idea'"
        },
        "position": {
          "name": "position",
          "type": "jsonb",
          "primaryKey": false,
          "notNull": false
        },
        "style": {
          "name": "style",
          "type": "jsonb",
          "primaryKey": false,
          "notNull": false
        },
        "reference_id": {
          "name": "reference_id",
          "type": "text",
          "primaryKey": false,
          "notNull": false
        },
        "created_at": {
          "name": "created_at",
          "type": "timestamp",
          "primaryKey": false,
          "notNull": false,
          "default": "now()"
        }
      },
      "indexes": {},
      "foreignKeys": {
        "mind_map_nodes_map_id_mind_maps_id_fk": {
          "name": "mind_map_nodes_map_id_mind_maps_id_fk",
          "tableFrom": "mind_map_nodes",
          "tableTo": "mind_maps",
          "columnsFrom": [
            "map_id"
          ],
          "columnsTo": [
            "id"
          ],
          "onDelete": "cascade",
          "onUpdate": "no action"
        }
      },
      "compositePrimaryKeys": {},
      "uniqueConstraints": {}
    },
    "public.mind_maps": {
      "name": "mind_maps",
      "schema": "",
      "columns": {
        "id": {
          "name": "id",
          "type": "text",
          "primaryKey": true,
          "notNull": true
        },
        "title": {
          "name": "title",
          "type": "text",
          "primaryKey": false,
          "notNull": true
        },
        "project_id": {
          "name": "project_id",
          "type": "text",
          "primaryKey": false,
          "notNull": false
        },
        "created_by": {
          "name": "created_by",
          "type": "text",
          "primaryKey": false,
          "notNull": false
        },
        "created_at": {
          "name": "created_at",
          "type": "timestamp",
          "primaryKey": false,
          "notNull": false,
          "default": "now()"
        },
        "updated_at": {
          "name": "updated_at",
          "type": "timestamp",
          "primaryKey": false,
          "notNull": false,
          "default": "now()"
        }
      },
      "indexes": {},
      "foreignKeys": {
        "mind_maps_project_id_projects_id_fk": {
          "name": "mind_maps_project_id_projects_id_fk",
          "tableFrom": "mind_maps",
          "tableTo": "projects",
          "columnsFrom": [
            "project_id"
          ],
          "columnsTo": [
            "id"
          ],
          "onDelete": "cascade",
          "onUpdate": "no action"
        }
      },
      "compositePrimaryKeys": {},
      "uniqueConstraints": {}
    },
    "public.papyrus_documents": {
      "name": "papyrus_documents",
      "schema": "",
      "columns": {
        "id": {
          "name": "id",
          "type": "text",
          "primaryKey": true,
          "notNull": true
        },
        "title": {
          "name": "title",
          "type": "text",
          "primaryKey": false,
          "notNull": true
        },
        "type": {
          "name": "type",
          "type": "text",
          "primaryKey": false,
          "notNull": false,
          "default": "'text'"
        },
        "content": {
          "name": "content",
          "type": "text",
          "primaryKey": false,
          "notNull": false
        },
        "file_url": {
          "name": "file_url",
          "type": "text",
          "primaryKey": false,
          "notNull": false
        },
        "document_type": {
          "name": "document_type",
          "type": "text",
          "primaryKey": false,
          "notNull": false,
          "default": "'note'"
        },
        "energy_level": {
          "name": "energy_level",
          "type": "integer",
          "primaryKey": false,
          "notNull": false
        },
        "mood": {
          "name": "mood",
          "type": "text",
          "primaryKey": false,
          "notNull": false
        },
        "tags": {
          "name": "tags",
          "type": "text",
          "primaryKey": false,
          "notNull": false
        },
        "insights": {
          "name": "insights",
          "type": "text",
          "primaryKey": false,
          "notNull": false
        },
        "project_id": {
          "name": "project_id",
          "type": "text",
          "primaryKey": false,
          "notNull": false
        },
        "author_id": {
          "name": "author_id",
          "type": "text",
          "primaryKey": false,
          "notNull": false
        },
        "status": {
          "name": "status",
          "type": "text",
          "primaryKey": false,
          "notNull": false,
          "default": "'active'"
        },
        "is_private": {
          "name": "is_private",
          "type": "boolean",
          "primaryKey": false,
          "notNull": false,
          "default": false
        },
        "related_tasks_count": {
          "name": "related_tasks_count",
          "type": "integer",
          "primaryKey": false,
          "notNull": false,
          "default": 0
        },
        "is_linked_to_task": {
          "name": "is_linked_to_task",
          "type": "boolean",
          "primaryKey": false,
          "notNull": false,
          "default": false
        },
        "created_at": {
          "name": "created_at",
          "type": "timestamp",
          "primaryKey": false,
          "notNull": false,
          "default": "now()"
        },
        "updated_at": {
          "name": "updated_at",
          "type": "timestamp",
          "primaryKey": false,
          "notNull": false,
          "default": "now()"
        }
      },
      "indexes": {},
      "foreignKeys": {
        "papyrus_documents_project_id_projects_id_fk": {
          "name": "papyrus_documents_project_id_projects_id_fk",
          "tableFrom": "papyrus_documents",
          "tableTo": "projects",
          "columnsFrom": [
            "project_id"
          ],
          "columnsTo": [
            "id"
          ],
          "onDelete": "cascade",
          "onUpdate": "no action"
        },
        "papyrus_documents_author_id_users_id_fk": {
          "name": "papyrus_documents_author_id_users_id_fk",
          "tableFrom": "papyrus_documents",
          "tableTo": "users",
          "columnsFrom": [
            "author_id"
          ],
          "columnsTo": [
            "id"
          ],
          "onDelete": "set null",
          "onUpdate": "no action"
        }
      },
      "compositePrimaryKeys": {},
      "uniqueConstraints": {}
    },
    "public.thoughts": {
      "name": "thoughts",
      "schema": "",
      "columns": {
        "id": {
          "name": "id",
          "type": "text",
          "primaryKey": true,
          "notNull": true
        },
        "content": {
          "name": "content",
          "type": "text",
          "primaryKey": false,
          "notNull": true
        },
        "is_processed": {
          "name": "is_processed",
          "type": "boolean",
          "primaryKey": false,
          "notNull": false,
          "default": false
        },
        "user_id": {
          "name": "user_id",
          "type": "text",
          "primaryKey": false,
          "notNull": false
        },
        "created_at": {
          "name": "created_at",
          "type": "timestamp",
          "primaryKey": false,
          "notNull": false,
          "default": "now()"
        }
      },
      "indexes": {},
      "foreignKeys": {},
      "compositePrimaryKeys": {},
      "uniqueConstraints": {}
    },
    "public.astral_profiles": {
      "name": "astral_profiles",
      "schema": "",
      "columns": {
        "id": {
          "name": "id",
          "type": "text",
          "primaryKey": true,
          "notNull": true
        },
        "user_id": {
          "name": "user_id",
          "type": "text",
          "primaryKey": false,
          "notNull": false
        },
        "sun_sign": {
          "name": "sun_sign",
          "type": "text",
          "primaryKey": false,
          "notNull": false
        },
        "moon_sign": {
          "name": "moon_sign",
          "type": "text",
          "primaryKey": false,
          "notNull": false
        },
        "rising_sign": {
          "name": "rising_sign",
          "type": "text",
          "primaryKey": false,
          "notNull": false
        },
        "birth_date": {
          "name": "birth_date",
          "type": "timestamp",
          "primaryKey": false,
          "notNull": false
        },
        "birth_time": {
          "name": "birth_time",
          "type": "text",
          "primaryKey": false,
          "notNull": false
        },
        "birth_place": {
          "name": "birth_place",
          "type": "text",
          "primaryKey": false,
          "notNull": false
        },
        "chart_data": {
          "name": "chart_data",
          "type": "jsonb",
          "primaryKey": false,
          "notNull": false
        },
        "updated_at": {
          "name": "updated_at",
          "type": "timestamp",
          "primaryKey": false,
          "notNull": false,
          "default": "now()"
        }
      },
      "indexes": {},
      "foreignKeys": {
        "astral_profiles_user_id_fk": {
          "name": "astral_profiles_user_id_fk",
          "tableFrom": "astral_profiles",
          "tableTo": "users",
          "columnsFrom": [
            "user_id"
          ],
          "columnsTo": [
            "id"
          ],
          "onDelete": "cascade",
          "onUpdate": "no action"
        }
      },
      "compositePrimaryKeys": {},
      "uniqueConstraints": {
        "astral_profiles_user_id_unique": {
          "name": "astral_profiles_user_id_unique",
          "nullsNotDistinct": false,
          "columns": [
            "user_id"
          ]
        }
      }
    },
    "public.diary_entries": {
      "name": "diary_entries",
      "schema": "",
      "columns": {
        "id": {
          "name": "id",
          "type": "text",
          "primaryKey": true,
          "notNull": true
        },
        "user_id": {
          "name": "user_id",
          "type": "text",
          "primaryKey": false,
          "notNull": true
        },
        "content": {
          "name": "content",
          "type": "text",
          "primaryKey": false,
          "notNull": true
        },
        "emotional_states": {
          "name": "emotional_states",
          "type": "jsonb",
          "primaryKey": false,
          "notNull": false
        },
        "linked_morning_energy_id": {
          "name": "linked_morning_energy_id",
          "type": "text",
          "primaryKey": false,
          "notNull": false
        },
        "linked_afternoon_energy_id": {
          "name": "linked_afternoon_energy_id",
          "type": "text",
          "primaryKey": false,
          "notNull": false
        },
        "entry_date": {
          "name": "entry_date",
          "type": "timestamp",
          "primaryKey": false,
          "notNull": true
        },
        "created_at": {
          "name": "created_at",
          "type": "timestamp",
          "primaryKey": false,
          "notNull": false,
          "default": "now()"
        },
        "updated_at": {
          "name": "updated_at",
          "type": "timestamp",
          "primaryKey": false,
          "notNull": false,
          "default": "now()"
        }
      },
      "indexes": {},
      "foreignKeys": {
        "diary_entries_user_id_fk": {
          "name": "diary_entries_user_id_fk",
          "tableFrom": "diary_entries",
          "tableTo": "users",
          "columnsFrom": [
            "user_id"
          ],
          "columnsTo": [
            "id"
          ],
          "onDelete": "cascade",
          "onUpdate": "no action"
        },
        "diary_entries_morning_energy_fk": {
          "name": "diary_entries_morning_energy_fk",
          "tableFrom": "diary_entries",
          "tableTo": "energy_checkins",
          "columnsFrom": [
            "linked_morning_energy_id"
          ],
          "columnsTo": [
            "id"
          ],
          "onDelete": "set null",
          "onUpdate": "no action"
        },
        "diary_entries_afternoon_energy_fk": {
          "name": "diary_entries_afternoon_energy_fk",
          "tableFrom": "diary_entries",
          "tableTo": "energy_checkins",
          "columnsFrom": [
            "linked_afternoon_energy_id"
          ],
          "columnsTo": [
            "id"
          ],
          "onDelete": "set null",
          "onUpdate": "no action"
        }
      },
      "compositePrimaryKeys": {},
      "uniqueConstraints": {}
    },
    "public.energy_checkins": {
      "name": "energy_checkins",
      "schema": "",
      "columns": {
        "id": {
          "name": "id",
          "type": "text",
          "primaryKey": true,
          "notNull": true
        },
        "user_id": {
          "name": "user_id",
          "type": "text",
          "primaryKey": false,
          "notNull": true
        },
        "time_of_day": {
          "name": "time_of_day",
          "type": "text",
          "primaryKey": false,
          "notNull": true
        },
        "energy_type": {
          "name": "energy_type",
          "type": "text",
          "primaryKey": false,
          "notNull": true
        },
        "energy_intensity": {
          "name": "energy_intensity",
          "type": "integer",
          "primaryKey": false,
          "notNull": true
        },
        "secondary_type": {
          "name": "secondary_type",
          "type": "text",
          "primaryKey": false,
          "notNull": false
        },
        "secondary_time": {
          "name": "secondary_time",
          "type": "timestamp",
          "primaryKey": false,
          "notNull": false
        },
        "secondary_intensity": {
          "name": "secondary_intensity",
          "type": "integer",
          "primaryKey": false,
          "notNull": false
        },
        "recorded_at": {
          "name": "recorded_at",
          "type": "timestamp",
          "primaryKey": false,
          "notNull": true
        },
        "created_at": {
          "name": "created_at",
          "type": "timestamp",
          "primaryKey": false,
          "notNull": false,
          "default": "now()"
        },
        "updated_at": {
          "name": "updated_at",
          "type": "timestamp",
          "primaryKey": false,
          "notNull": false,
          "default": "now()"
        }
      },
      "indexes": {},
      "foreignKeys": {
        "energy_checkins_user_id_fk": {
          "name": "energy_checkins_user_id_fk",
          "tableFrom": "energy_checkins",
          "tableTo": "users",
          "columnsFrom": [
            "user_id"
          ],
          "columnsTo": [
            "id"
          ],
          "onDelete": "cascade",
          "onUpdate": "no action"
        }
      },
      "compositePrimaryKeys": {},
      "uniqueConstraints": {}
    },
    "public.menstrual_cycles": {
      "name": "menstrual_cycles",
      "schema": "",
      "columns": {
        "id": {
          "name": "id",
          "type": "text",
          "primaryKey": true,
          "notNull": true
        },
        "user_id": {
          "name": "user_id",
          "type": "text",
          "primaryKey": false,
          "notNull": true
        },
        "start_date": {
          "name": "start_date",
          "type": "timestamp",
          "primaryKey": false,
          "notNull": true
        },
        "notes": {
          "name": "notes",
          "type": "text",
          "primaryKey": false,
          "notNull": false
        },
        "created_at": {
          "name": "created_at",
          "type": "timestamp",
          "primaryKey": false,
          "notNull": false,
          "default": "now()"
        },
        "updated_at": {
          "name": "updated_at",
          "type": "timestamp",
          "primaryKey": false,
          "notNull": false,
          "default": "now()"
        }
      },
      "indexes": {},
      "foreignKeys": {
        "menstrual_cycles_user_id_fk": {
          "name": "menstrual_cycles_user_id_fk",
          "tableFrom": "menstrual_cycles",
          "tableTo": "users",
          "columnsFrom": [
            "user_id"
          ],
          "columnsTo": [
            "id"
          ],
          "onDelete": "cascade",
          "onUpdate": "no action"
        }
      },
      "compositePrimaryKeys": {},
      "uniqueConstraints": {}
    },
    "public.rituals": {
      "name": "rituals",
      "schema": "",
      "columns": {
        "id": {
          "name": "id",
          "type": "text",
          "primaryKey": true,
          "notNull": true
        },
        "user_id": {
          "name": "user_id",
          "type": "text",
          "primaryKey": false,
          "notNull": true
        },
        "name": {
          "name": "name",
          "type": "text",
          "primaryKey": false,
          "notNull": true
        },
        "description": {
          "name": "description",
          "type": "text",
          "primaryKey": false,
          "notNull": false
        },
        "morning_energy": {
          "name": "morning_energy",
          "type": "jsonb",
          "primaryKey": false,
          "notNull": false
        },
        "afternoon_energy": {
          "name": "afternoon_energy",
          "type": "jsonb",
          "primaryKey": false,
          "notNull": false
        },
        "evening_states": {
          "name": "evening_states",
          "type": "jsonb",
          "primaryKey": false,
          "notNull": false
        },
        "day_of_week": {
          "name": "day_of_week",
          "type": "text",
          "primaryKey": false,
          "notNull": false
        },
        "detection_score": {
          "name": "detection_score",
          "type": "integer",
          "primaryKey": false,
          "notNull": false
        },
        "efficiency_score": {
          "name": "efficiency_score",
          "type": "integer",
          "primaryKey": false,
          "notNull": false
        },
        "completion_rate": {
          "name": "completion_rate",
          "type": "integer",
          "primaryKey": false,
          "notNull": false
        },
        "is_active": {
          "name": "is_active",
          "type": "boolean",
          "primaryKey": false,
          "notNull": false,
          "default": true
        },
        "auto_reminder": {
          "name": "auto_reminder",
          "type": "boolean",
          "primaryKey": false,
          "notNull": false,
          "default": false
        },
        "reminder_time": {
          "name": "reminder_time",
          "type": "text",
          "primaryKey": false,
          "notNull": false
        },
        "occurrences": {
          "name": "occurrences",
          "type": "integer",
          "primaryKey": false,
          "notNull": false,
          "default": 1
        },
        "last_activated_at": {
          "name": "last_activated_at",
          "type": "timestamp",
          "primaryKey": false,
          "notNull": false
        },
        "created_at": {
          "name": "created_at",
          "type": "timestamp",
          "primaryKey": false,
          "notNull": false,
          "default": "now()"
        },
        "updated_at": {
          "name": "updated_at",
          "type": "timestamp",
          "primaryKey": false,
          "notNull": false,
          "default": "now()"
        }
      },
      "indexes": {},
      "foreignKeys": {
        "rituals_user_id_fk": {
          "name": "rituals_user_id_fk",
          "tableFrom": "rituals",
          "tableTo": "users",
          "columnsFrom": [
            "user_id"
          ],
          "columnsTo": [
            "id"
          ],
          "onDelete": "cascade",
          "onUpdate": "no action"
        }
      },
      "compositePrimaryKeys": {},
      "uniqueConstraints": {}
    },
    "public.channel_messages": {
      "name": "channel_messages",
      "schema": "",
      "columns": {
        "id": {
          "name": "id",
          "type": "text",
          "primaryKey": true,
          "notNull": true
        },
        "channel_id": {
          "name": "channel_id",
          "type": "text",
          "primaryKey": false,
          "notNull": true
        },
        "user_id": {
          "name": "user_id",
          "type": "text",
          "primaryKey": false,
          "notNull": true
        },
        "content": {
          "name": "content",
          "type": "text",
          "primaryKey": false,
          "notNull": true
        },
        "attachments": {
          "name": "attachments",
          "type": "jsonb",
          "primaryKey": false,
          "notNull": false
        },
        "created_at": {
          "name": "created_at",
          "type": "timestamp",
          "primaryKey": false,
          "notNull": false,
          "default": "now()"
        }
      },
      "indexes": {},
      "foreignKeys": {
        "channel_messages_channel_id_project_channels_id_fk": {
          "name": "channel_messages_channel_id_project_channels_id_fk",
          "tableFrom": "channel_messages",
          "tableTo": "project_channels",
          "columnsFrom": [
            "channel_id"
          ],
          "columnsTo": [
            "id"
          ],
          "onDelete": "cascade",
          "onUpdate": "no action"
        },
        "channel_messages_user_id_users_id_fk": {
          "name": "channel_messages_user_id_users_id_fk",
          "tableFrom": "channel_messages",
          "tableTo": "users",
          "columnsFrom": [
            "user_id"
          ],
          "columnsTo": [
            "id"
          ],
          "onDelete": "no action",
          "onUpdate": "no action"
        }
      },
      "compositePrimaryKeys": {},
      "uniqueConstraints": {}
    },
    "public.nexus_chats": {
      "name": "nexus_chats",
      "schema": "",
      "columns": {
        "id": {
          "name": "id",
          "type": "text",
          "primaryKey": true,
          "notNull": true
        },
        "user_id": {
          "name": "user_id",
          "type": "text",
          "primaryKey": false,
          "notNull": true
        },
        "title": {
          "name": "title",
          "type": "text",
          "primaryKey": false,
          "notNull": false,
          "default": "'Nova Conversa'"
        },
        "context": {
          "name": "context",
          "type": "jsonb",
          "primaryKey": false,
          "notNull": false,
          "default": "'{}'::jsonb"
        },
        "is_archived": {
          "name": "is_archived",
          "type": "boolean",
          "primaryKey": false,
          "notNull": false,
          "default": false
        },
        "created_at": {
          "name": "created_at",
          "type": "timestamp",
          "primaryKey": false,
          "notNull": true,
          "default": "now()"
        },
        "updated_at": {
          "name": "updated_at",
          "type": "timestamp",
          "primaryKey": false,
          "notNull": false,
          "default": "now()"
        }
      },
      "indexes": {},
      "foreignKeys": {
        "nexus_chats_user_id_users_id_fk": {
          "name": "nexus_chats_user_id_users_id_fk",
          "tableFrom": "nexus_chats",
          "tableTo": "users",
          "columnsFrom": [
            "user_id"
          ],
          "columnsTo": [
            "id"
          ],
          "onDelete": "cascade",
          "onUpdate": "no action"
        }
      },
      "compositePrimaryKeys": {},
      "uniqueConstraints": {}
    },
    "public.nexus_messages": {
      "name": "nexus_messages",
      "schema": "",
      "columns": {
        "id": {
          "name": "id",
          "type": "text",
          "primaryKey": true,
          "notNull": true
        },
        "nexus_id": {
          "name": "nexus_id",
          "type": "text",
          "primaryKey": false,
          "notNull": true
        },
        "role": {
          "name": "role",
          "type": "text",
          "primaryKey": false,
          "notNull": true
        },
        "content": {
          "name": "content",
          "type": "text",
          "primaryKey": false,
          "notNull": false
        },
        "tool_response": {
          "name": "tool_response",
          "type": "jsonb",
          "primaryKey": false,
          "notNull": false
        },
        "file_urls": {
          "name": "file_urls",
          "type": "jsonb",
          "primaryKey": false,
          "notNull": false,
          "default": "'[]'::jsonb"
        },
        "created_at": {
          "name": "created_at",
          "type": "timestamp",
          "primaryKey": false,
          "notNull": true,
          "default": "now()"
        }
      },
      "indexes": {},
      "foreignKeys": {
        "nexus_messages_nexus_id_nexus_chats_id_fk": {
          "name": "nexus_messages_nexus_id_nexus_chats_id_fk",
          "tableFrom": "nexus_messages",
          "tableTo": "nexus_chats",
          "columnsFrom": [
            "nexus_id"
          ],
          "columnsTo": [
            "id"
          ],
          "onDelete": "cascade",
          "onUpdate": "no action"
        }
      },
      "compositePrimaryKeys": {},
      "uniqueConstraints": {}
    },
    "public.project_channels": {
      "name": "project_channels",
      "schema": "",
      "columns": {
        "id": {
          "name": "id",
          "type": "text",
          "primaryKey": true,
          "notNull": true
        },
        "project_id": {
          "name": "project_id",
          "type": "text",
          "primaryKey": false,
          "notNull": true
        },
        "name": {
          "name": "name",
          "type": "text",
          "primaryKey": false,
          "notNull": false,
          "default": "'general'"
        },
        "created_at": {
          "name": "created_at",
          "type": "timestamp",
          "primaryKey": false,
          "notNull": false,
          "default": "now()"
        }
      },
      "indexes": {},
      "foreignKeys": {
        "project_channels_project_id_projects_id_fk": {
          "name": "project_channels_project_id_projects_id_fk",
          "tableFrom": "project_channels",
          "tableTo": "projects",
          "columnsFrom": [
            "project_id"
          ],
          "columnsTo": [
            "id"
          ],
          "onDelete": "cascade",
          "onUpdate": "no action"
        }
      },
      "compositePrimaryKeys": {},
      "uniqueConstraints": {}
    },
    "public.events": {
      "name": "events",
      "schema": "",
      "columns": {
        "id": {
          "name": "id",
          "type": "text",
          "primaryKey": true,
          "notNull": true
        },
        "created_by": {
          "name": "created_by",
          "type": "text",
          "primaryKey": false,
          "notNull": true
        },
        "title": {
          "name": "title",
          "type": "text",
          "primaryKey": false,
          "notNull": true
        },
        "description": {
          "name": "description",
          "type": "text",
          "primaryKey": false,
          "notNull": false
        },
        "date": {
          "name": "date",
          "type": "text",
          "primaryKey": false,
          "notNull": true
        },
        "project_id": {
          "name": "project_id",
          "type": "text",
          "primaryKey": false,
          "notNull": false
        },
        "created_at": {
          "name": "created_at",
          "type": "timestamp (3)",
          "primaryKey": false,
          "notNull": false
        },
        "updated_at": {
          "name": "updated_at",
          "type": "timestamp (3)",
          "primaryKey": false,
          "notNull": false
        },
        "deleted_at": {
          "name": "deleted_at",
          "type": "timestamp (3)",
          "primaryKey": false,
          "notNull": false
        }
      },
      "indexes": {},
      "foreignKeys": {
        "events_created_by_users_id_fk": {
          "name": "events_created_by_users_id_fk",
          "tableFrom": "events",
          "tableTo": "users",
          "columnsFrom": [
            "created_by"
          ],
          "columnsTo": [
            "id"
          ],
          "onDelete": "no action",
          "onUpdate": "no action"
        }
      },
      "compositePrimaryKeys": {},
      "uniqueConstraints": {}
    }
  },
  "enums": {},
  "schemas": {},
  "sequences": {},
  "_meta": {
    "columns": {},
    "schemas": {},
    "tables": {}
  }
}